{"enemySlots": [3, 3, 0, 0, 0, 0, 0, 0, 0, 0, 0], "alternatives": {"Explorers,Painted World of Ariamis,Darkroot,Dark Souls The Board Game": [[17, 21, 11, 16, 9, 11], [17, 9, 11, 16, 24, 11], [17, 21, 11, 16, 25, 14], [17, 14, 6, 16, 21, 11], [17, 14, 6, 20, 21, 11], [17, 21, 11, 16, 22, 11]], "Painted World of Ariamis,Darkroot,Tomb of Giants,Dark Souls The Board Game": [[17, 28, 6, 16, 24, 21], [17, 28, 21, 16, 28, 21], [17, 28, 21, 16, 9, 28], [17, 28, 14, 16, 9, 28], [17, 28, 14, 16, 25, 21], [17, 9, 6, 16, 9, 28]], "Explorers,Dark Souls The Board Game": [[16, 14, 6, 16, 14, 11], [16, 14, 11, 16, 25, 14], [16, 14, 11, 16, 14, 11]], "Darkroot,Tomb of Giants,Dark Souls The Board Game": [[17, 28, 14, 16, 28, 14], [17, 14, 6, 13, 14, 6], [17, 28, 14, 16, 25, 14], [17, 14, 6, 16, 28, 14], [17, 28, 6, 16, 24, 14]], "Explorers,Painted World of Ariamis,Dark Souls The Board Game": [[16, 14, 6, 16, 9, 11], [16, 14, 11, 16, 21, 11], [16, 21, 11, 16, 21, 11], [16, 21, 6, 16, 21, 11], [16, 9, 6, 16, 9, 11], [16, 21, 6, 16, 9, 11]], "Painted World of Ariamis,Darkroot,Dark Souls The Board Game": [[17, 9, 6, 16, 9, 6], [17, 14, 6, 20, 14, 6], [17, 21, 6, 16, 25, 14], [17, 9, 6, 16, 25, 21], [17, 9, 6, 16, 25, 14], [17, 21, 6, 16, 22, 6]], "Explorers,Darkroot,Tomb of Giants,Painted World of Ariamis": [[17, 21, 11, 13, 21, 11]], "Explorers,Darkroot,Dark Souls The Board Game,Iron Keep": [[17, 14, 11, 16, 1, 14]], "Explorers,Painted World of Ariamis,Tomb of Giants,Dark Souls The Board Game": [[16, 21, 11, 16, 28, 21], [16, 28, 11, 16, 9, 14], [16, 21, 11, 16, 28, 14]], "Explorers,Darkroot,Dark Souls The Board Game": [[17, 14, 6, 16, 24, 11], [17, 24, 6, 16, 24, 11], [17, 14, 11, 16, 24, 11], [17, 14, 11, 16, 22, 11], [17, 14, 11, 16, 25, 14], [17, 24, 11, 16, 24, 11]], "Explorers,Darkroot,Painted World of Ariamis,Tomb of Giants,Dark Souls The Board Game": [[17, 9, 11, 16, 9, 28], [17, 14, 11, 13, 21, 11], [17, 21, 11, 16, 28, 14], [17, 21, 6, 13, 21, 11], [17, 14, 6, 13, 21, 11], [17, 28, 11, 16, 24, 21]], "Painted World of Ariamis,Tomb of Giants,Dark Souls The Board Game": [[16, 21, 6, 16, 28, 21], [16, 21, 6, 16, 28, 14], [16, 28, 6, 16, 9, 14]], "Darkroot,Dark Souls The Board Game,Iron Keep": [[17, 14, 6, 16, 1, 14]], "Tomb of Giants,Dark Souls The Board Game": [[16, 14, 6, 16, 28, 14]], "Explorers,Darkroot,Tomb of Giants,Dark Souls The Board Game": [[17, 14, 11, 16, 28, 14], [17, 14, 6, 13, 14, 11], [17, 28, 11, 16, 24, 14], [17, 14, 11, 13, 14, 11]], "Painted World of Ariamis,Dark Souls The Board Game": [[16, 9, 6, 16, 9, 6], [16, 21, 6, 16, 21, 6], [16, 21, 6, 16, 25, 14], [16, 21, 6, 16, 25, 21], [16, 21, 6, 16, 9, 6], [16, 14, 6, 16, 21, 6]], "Darkroot,Dark Souls The Board Game": [[17, 14, 6, 16, 14, 6], [17, 14, 6, 16, 22, 6], [17, 25, 6, 16, 24, 14], [16, 14, 6, 16, 24, 6], [17, 14, 6, 16, 25, 14], [17, 14, 6, 16, 24, 6]], "Dark Souls The Board Game": [[16, 14, 6, 16, 25, 14], [16, 14, 6, 16, 14, 6]], "Explorers,Tomb of Giants,Dark Souls The Board Game": [[16, 14, 11, 16, 28, 14]], "Explorers,Painted World of Ariamis,Darkroot,The Sunless City": [[17, 14, 6, 20, 21, 11]], "Darkroot,Tomb of Giants,The Sunless City": [[17, 14, 6, 13, 14, 6]], "Painted World of Ariamis,Darkroot,The Sunless City": [[17, 14, 6, 20, 14, 6]], "Explorers,Darkroot,Painted World of Ariamis,Tomb of Giants,The Sunless City": [[17, 14, 11, 13, 21, 11], [17, 21, 6, 13, 21, 11], [17, 14, 6, 13, 21, 11]], "Explorers,Darkroot,Tomb of Giants,The Sunless City": [[17, 14, 6, 13, 14, 11], [17, 14, 11, 13, 14, 11]]}, "original": [16, 14, 6, 16, 14, 6]}