{"enemySlots": [3, 3, 0, 0, 0, 0, 0, 0, 0, 0, 0], "alternatives": {"Darkroot,Dark Souls The Board Game,Explorers,Painted World of Ariamis": [[17, 14, 11, 16, 21, 11], [17, 21, 6, 16, 22, 11], [17, 21, 6, 16, 21, 11], [17, 21, 11, 16, 9, 11], [17, 14, 6, 16, 9, 11], [17, 9, 6, 16, 9, 11], [17, 21, 6, 16, 24, 11], [17, 21, 6, 16, 9, 11], [16, 21, 6, 16, 24, 11], [17, 14, 6, 16, 21, 11], [17, 9, 11, 16, 25, 21], [17, 14, 11, 20, 21, 11], [17, 9, 11, 16, 25, 14], [17, 21, 11, 16, 25, 21], [17, 9, 6, 16, 24, 11], [17, 9, 11, 16, 24, 11], [17, 14, 11, 16, 9, 11], [16, 21, 11, 16, 24, 11], [17, 21, 11, 16, 25, 14], [17, 21, 11, 16, 24, 11], [17, 21, 11, 16, 22, 11], [17, 21, 11, 16, 21, 11], [17, 14, 6, 20, 21, 11]], "Dark Souls The Board Game,Painted World of Ariamis": [[16, 21, 6, 16, 25, 14], [16, 21, 6, 16, 25, 21], [16, 21, 6, 16, 9, 6], [16, 14, 6, 16, 21, 6], [16, 14, 6, 16, 9, 6], [16, 21, 6, 16, 21, 6], [16, 9, 6, 16, 9, 6]], "Darkroot,Dark Souls The Board Game,Explorers": [[17, 25, 11, 16, 24, 14], [16, 14, 6, 16, 24, 11], [17, 14, 6, 16, 14, 11], [17, 24, 6, 16, 24, 11], [16, 14, 11, 16, 24, 11], [17, 14, 11, 16, 25, 14], [17, 14, 6, 16, 24, 11], [17, 14, 6, 16, 22, 11], [17, 14, 11, 16, 22, 11], [17, 24, 11, 16, 24, 11], [17, 14, 11, 16, 24, 11], [17, 14, 11, 16, 14, 11]], "Darkroot,Dark Souls The Board Game,Painted World of Ariamis": [[17, 21, 6, 16, 25, 21], [17, 21, 6, 16, 21, 6], [17, 9, 6, 16, 25, 14], [17, 9, 6, 16, 25, 21], [17, 21, 6, 16, 25, 14], [17, 14, 6, 16, 21, 6], [17, 21, 6, 16, 9, 6], [17, 14, 6, 16, 9, 6], [17, 14, 6, 20, 21, 6], [17, 21, 6, 16, 24, 6], [16, 21, 6, 16, 24, 6], [17, 14, 6, 20, 14, 6], [17, 9, 6, 16, 24, 6], [17, 21, 6, 16, 22, 6], [17, 9, 6, 16, 9, 6]], "Darkroot,Dark Souls The Board Game,Tomb of Giants": [[17, 28, 6, 16, 24, 14], [17, 14, 6, 13, 14, 6], [17, 14, 6, 16, 28, 14], [17, 28, 14, 16, 25, 14], [17, 28, 14, 16, 28, 14]], "Darkroot,Dark Souls The Board Game,Tomb of Giants,Painted World of Ariamis": [[17, 28, 6, 16, 9, 21], [17, 28, 6, 16, 24, 21], [17, 14, 6, 13, 21, 6], [17, 28, 6, 16, 9, 14], [17, 21, 6, 16, 28, 21], [17, 21, 6, 16, 28, 14], [17, 28, 14, 16, 9, 28], [17, 28, 21, 16, 28, 21], [17, 28, 21, 16, 25, 21], [17, 28, 14, 16, 28, 21], [17, 28, 14, 16, 25, 21], [17, 28, 21, 16, 9, 28], [17, 21, 6, 13, 21, 6], [17, 9, 6, 16, 9, 28]], "Darkroot,Dark Souls The Board Game": [[17, 24, 6, 16, 24, 6], [17, 25, 6, 16, 24, 14], [17, 14, 6, 16, 22, 6], [17, 14, 6, 16, 25, 14], [17, 14, 6, 16, 24, 6], [17, 14, 6, 16, 14, 6], [16, 14, 6, 16, 24, 6]], "Explorers,Tomb of Giants,Darkroot,Dark Souls The Board Game,Painted World of Ariamis": [[17, 28, 11, 16, 9, 14], [17, 21, 11, 16, 28, 21], [17, 14, 11, 13, 21, 11], [17, 28, 11, 16, 24, 21], [17, 28, 11, 16, 9, 21], [17, 21, 6, 13, 21, 11], [17, 21, 11, 16, 28, 14], [17, 14, 6, 13, 21, 11], [17, 9, 11, 16, 9, 28]], "Dark Souls The Board Game": [[16, 14, 6, 16, 25, 14], [16, 14, 6, 16, 14, 6]], "Dark Souls The Board Game,Explorers,Tomb of Giants": [[16, 14, 11, 16, 28, 14]], "Dark Souls The Board Game,Explorers,Painted World of Ariamis": [[16, 14, 6, 16, 9, 11], [16, 21, 11, 16, 25, 14], [16, 14, 11, 16, 21, 11], [16, 14, 11, 16, 9, 11], [16, 21, 6, 16, 9, 11], [16, 14, 6, 16, 21, 11], [16, 21, 11, 16, 25, 21], [16, 21, 6, 16, 21, 11], [16, 21, 11, 16, 9, 11], [16, 9, 6, 16, 9, 11], [16, 21, 11, 16, 21, 11], [16, 9, 11, 16, 9, 11]], "Darkroot,Dark Souls The Board Game,Explorers,Tomb of Giants": [[17, 14, 11, 16, 28, 14], [17, 28, 11, 16, 24, 14], [17, 14, 6, 13, 14, 11], [17, 14, 11, 13, 14, 11]], "Dark Souls The Board Game,Painted World of Ariamis,Tomb of Giants": [[16, 21, 6, 16, 28, 21], [16, 21, 6, 16, 28, 14], [16, 28, 6, 16, 9, 14]], "Darkroot,Dark Souls The Board Game,Iron Keep": [[17, 14, 6, 16, 1, 14]], "Dark Souls The Board Game,Explorers,Tomb of Giants,Painted World of Ariamis": [[16, 21, 11, 16, 28, 14], [16, 21, 11, 16, 28, 21], [16, 28, 11, 16, 9, 14]], "Dark Souls The Board Game,Explorers": [[16, 14, 11, 16, 25, 14], [16, 14, 6, 16, 14, 11], [16, 14, 11, 16, 14, 11]], "Darkroot,Dark Souls The Board Game,Explorers,Iron Keep": [[17, 14, 11, 16, 1, 14]], "Darkroot,Explorers,Tomb of Giants,Painted World of Ariamis": [[17, 21, 11, 13, 21, 11]], "Dark Souls The Board Game,Tomb of Giants": [[16, 14, 6, 16, 28, 14]], "Darkroot,The Sunless City,Explorers,Painted World of Ariamis": [[17, 14, 11, 16, 21, 11], [17, 21, 6, 16, 22, 11], [17, 21, 6, 16, 21, 11], [17, 21, 11, 16, 9, 11], [17, 14, 6, 16, 9, 11], [17, 9, 6, 16, 9, 11], [17, 21, 6, 16, 24, 11], [17, 21, 6, 16, 9, 11], [16, 21, 6, 16, 24, 11], [17, 14, 6, 16, 21, 11], [17, 9, 11, 16, 25, 21], [17, 14, 11, 20, 21, 11], [17, 9, 11, 16, 25, 14], [17, 21, 11, 16, 25, 21], [17, 9, 6, 16, 24, 11], [17, 9, 11, 16, 24, 11], [17, 14, 11, 16, 9, 11], [16, 21, 11, 16, 24, 11], [17, 21, 11, 16, 25, 14], [17, 21, 11, 16, 24, 11], [17, 21, 11, 16, 22, 11], [17, 21, 11, 16, 21, 11], [17, 14, 6, 20, 21, 11]], "The Sunless City,Painted World of Ariamis": [[16, 21, 6, 16, 25, 14], [16, 21, 6, 16, 25, 21], [16, 21, 6, 16, 9, 6], [16, 14, 6, 16, 21, 6], [16, 14, 6, 16, 9, 6], [16, 21, 6, 16, 21, 6], [16, 9, 6, 16, 9, 6]], "Darkroot,The Sunless City,Explorers": [[17, 25, 11, 16, 24, 14], [16, 14, 6, 16, 24, 11], [17, 14, 6, 16, 14, 11], [17, 24, 6, 16, 24, 11], [16, 14, 11, 16, 24, 11], [17, 14, 11, 16, 25, 14], [17, 14, 6, 16, 24, 11], [17, 14, 6, 16, 22, 11], [17, 14, 11, 16, 22, 11], [17, 24, 11, 16, 24, 11], [17, 14, 11, 16, 24, 11], [17, 14, 11, 16, 14, 11]], "Darkroot,The Sunless City,Painted World of Ariamis": [[17, 21, 6, 16, 25, 21], [17, 21, 6, 16, 21, 6], [17, 9, 6, 16, 25, 14], [17, 9, 6, 16, 25, 21], [17, 21, 6, 16, 25, 14], [17, 14, 6, 16, 21, 6], [17, 21, 6, 16, 9, 6], [17, 14, 6, 16, 9, 6], [17, 14, 6, 20, 21, 6], [17, 21, 6, 16, 24, 6], [16, 21, 6, 16, 24, 6], [17, 14, 6, 20, 14, 6], [17, 9, 6, 16, 24, 6], [17, 21, 6, 16, 22, 6], [17, 9, 6, 16, 9, 6]], "Darkroot,The Sunless City,Tomb of Giants": [[17, 28, 6, 16, 24, 14], [17, 14, 6, 13, 14, 6], [17, 14, 6, 16, 28, 14], [17, 28, 14, 16, 25, 14], [17, 28, 14, 16, 28, 14]], "Darkroot,The Sunless City,Tomb of Giants,Painted World of Ariamis": [[17, 28, 6, 16, 9, 21], [17, 28, 6, 16, 24, 21], [17, 14, 6, 13, 21, 6], [17, 28, 6, 16, 9, 14], [17, 21, 6, 16, 28, 21], [17, 21, 6, 16, 28, 14], [17, 28, 14, 16, 9, 28], [17, 28, 21, 16, 28, 21], [17, 28, 21, 16, 25, 21], [17, 28, 14, 16, 28, 21], [17, 28, 14, 16, 25, 21], [17, 28, 21, 16, 9, 28], [17, 21, 6, 13, 21, 6], [17, 9, 6, 16, 9, 28]], "Darkroot,The Sunless City": [[17, 24, 6, 16, 24, 6], [17, 25, 6, 16, 24, 14], [17, 14, 6, 16, 22, 6], [17, 14, 6, 16, 25, 14], [17, 14, 6, 16, 24, 6], [17, 14, 6, 16, 14, 6], [16, 14, 6, 16, 24, 6]], "Explorers,Tomb of Giants,Darkroot,The Sunless City,Painted World of Ariamis": [[17, 28, 11, 16, 9, 14], [17, 21, 11, 16, 28, 21], [17, 14, 11, 13, 21, 11], [17, 28, 11, 16, 24, 21], [17, 28, 11, 16, 9, 21], [17, 21, 6, 13, 21, 11], [17, 21, 11, 16, 28, 14], [17, 14, 6, 13, 21, 11], [17, 9, 11, 16, 9, 28]], "The Sunless City": [[16, 14, 6, 16, 25, 14], [16, 14, 6, 16, 14, 6]], "The Sunless City,Explorers,Tomb of Giants": [[16, 14, 11, 16, 28, 14]], "The Sunless City,Explorers,Painted World of Ariamis": [[16, 14, 6, 16, 9, 11], [16, 21, 11, 16, 25, 14], [16, 14, 11, 16, 21, 11], [16, 14, 11, 16, 9, 11], [16, 21, 6, 16, 9, 11], [16, 14, 6, 16, 21, 11], [16, 21, 11, 16, 25, 21], [16, 21, 6, 16, 21, 11], [16, 21, 11, 16, 9, 11], [16, 9, 6, 16, 9, 11], [16, 21, 11, 16, 21, 11], [16, 9, 11, 16, 9, 11]], "Darkroot,The Sunless City,Explorers,Tomb of Giants": [[17, 14, 11, 16, 28, 14], [17, 28, 11, 16, 24, 14], [17, 14, 6, 13, 14, 11], [17, 14, 11, 13, 14, 11]], "The Sunless City,Painted World of Ariamis,Tomb of Giants": [[16, 21, 6, 16, 28, 21], [16, 21, 6, 16, 28, 14], [16, 28, 6, 16, 9, 14]], "Darkroot,The Sunless City,Iron Keep": [[17, 14, 6, 16, 1, 14]], "The Sunless City,Explorers,Tomb of Giants,Painted World of Ariamis": [[16, 21, 11, 16, 28, 14], [16, 21, 11, 16, 28, 21], [16, 28, 11, 16, 9, 14]], "The Sunless City,Explorers": [[16, 14, 11, 16, 25, 14], [16, 14, 6, 16, 14, 11], [16, 14, 11, 16, 14, 11]], "Darkroot,The Sunless City,Explorers,Iron Keep": [[17, 14, 11, 16, 1, 14]], "The Sunless City,Tomb of Giants": [[16, 14, 6, 16, 28, 14]]}, "original": [16, 14, 6, 16, 14, 6]}