{"enemySlots": [1, 2, 0, 0, 0, 0, 0, 0, 0, 0, 0], "alternatives": {"Painted World of Ariamis,Tomb of Giants,Executioner Chariot": [[10, 9, 13], [10, 21, 13]], "Dark Souls The Board Game,Darkroot": [[27, 24, 16], [8, 14, 17], [22, 14, 17]], "Tomb of Giants,Darkroot": [[8, 22, 13], [30, 22, 13], [22, 22, 13]], "Tomb of Giants,Dark Souls The Board Game,Darkroot": [[22, 14, 13], [24, 14, 13], [30, 14, 17]], "Executioner Chariot,Painted World of Ariamis,Darkroot": [[10, 9, 17], [10, 21, 17]], "Tomb of Giants,Explorers,Painted World of Ariamis": [[26, 21, 13]], "Dark Souls The Board Game,Explorers,Painted World of Ariamis": [[26, 21, 16], [26, 9, 16]], "Painted World of Ariamis,Darkroot": [[22, 21, 17], [24, 9, 17], [8, 21, 17]], "Darkroot": [[8, 8, 17], [8, 22, 17], [8, 24, 17]], "Painted World of Ariamis": [[21, 21, 20], [9, 9, 20], [9, 21, 20]], "Painted World of Ariamis,Tomb of Giants": [[30, 9, 13], [30, 21, 20], [9, 9, 13]], "Iron Keep,Dark Souls The Board Game": [[3, 14, 16]], "Tomb of Giants": [[30, 30, 13]], "Iron Keep,Dark Souls The Board Game,Darkroot": [[3, 14, 17], [3, 24, 16], [3, 8, 16]], "Executioner Chariot,Painted World of Ariamis,Dark Souls The Board Game": [[10, 14, 20]], "Executioner Chariot,Explorers,Dark Souls The Board Game": [[26, 10, 16]], "Dark Souls The Board Game,Explorers,Darkroot": [[26, 8, 16], [26, 24, 16], [26, 22, 16]], "Executioner Chariot,Dark Souls The Board Game": [[27, 10, 16], [10, 10, 16]], "Executioner Chariot,Tomb of Giants": [[30, 10, 13], [10, 10, 13]], "Dark Souls The Board Game,Painted World of Ariamis,Darkroot": [[24, 14, 20], [27, 21, 17], [8, 14, 20]], "Dark Souls The Board Game,Tomb of Giants": [[30, 14, 13], [30, 30, 16], [27, 30, 16]], "Executioner Chariot,Tomb of Giants,Darkroot": [[10, 8, 13], [10, 24, 13], [10, 22, 13]], "Painted World of Ariamis,Dark Souls The Board Game": [[5, 14, 16], [5, 21, 16], [27, 21, 16]], "Painted World of Ariamis,Tomb of Giants,Darkroot": [[24, 9, 13], [22, 9, 13], [30, 9, 17]], "Executioner Chariot,Tomb of Giants,Dark Souls The Board Game": [[30, 10, 16], [10, 14, 13]], "Iron Keep,Executioner Chariot,Dark Souls The Board Game": [[3, 10, 16]], "Dark Souls The Board Game": [[27, 14, 16]], "Executioner Chariot,Darkroot": [[10, 24, 17], [10, 10, 17], [10, 22, 17]], "Iron Keep,Painted World of Ariamis,Darkroot": [[3, 21, 17]], "Executioner Chariot,Painted World of Ariamis": [[10, 21, 20]], "Executioner Chariot,Dark Souls The Board Game,Darkroot": [[10, 14, 17], [10, 8, 16]], "Painted World of Ariamis,Explorers,Darkroot": [[26, 21, 17]], "Tomb of Giants,Explorers,Dark Souls The Board Game": [[26, 14, 13], [26, 30, 16]], "Iron Keep,Tomb of Giants,Painted World of Ariamis": [[3, 21, 13]], "Iron Keep,Tomb of Giants,Dark Souls The Board Game": [[3, 14, 13], [3, 30, 16]], "Dark Souls The Board Game,Explorers": [[26, 14, 16]], "Tomb of Giants,Painted World of Ariamis,Dark Souls The Board Game": [[27, 21, 13], [30, 14, 20]], "Iron Keep,Painted World of Ariamis,Dark Souls The Board Game": [[3, 21, 16], [3, 9, 16]], "The Sunless City,Darkroot": [[27, 24, 16], [8, 14, 17], [22, 14, 17]], "Tomb of Giants,The Sunless City,Darkroot": [[22, 14, 13], [24, 14, 13], [30, 14, 17]], "The Sunless City,Explorers,Painted World of Ariamis": [[26, 21, 16], [26, 9, 16]], "Iron Keep,The Sunless City": [[3, 14, 16]], "Iron Keep,The Sunless City,Darkroot": [[3, 14, 17], [3, 24, 16], [3, 8, 16]], "Executioner Chariot,Painted World of Ariamis,The Sunless City": [[10, 14, 20]], "Executioner Chariot,Explorers,The Sunless City": [[26, 10, 16]], "The Sunless City,Explorers,Darkroot": [[26, 8, 16], [26, 24, 16], [26, 22, 16]], "Executioner Chariot,The Sunless City": [[27, 10, 16], [10, 10, 16]], "The Sunless City,Painted World of Ariamis,Darkroot": [[24, 14, 20], [27, 21, 17], [8, 14, 20]], "The Sunless City,Tomb of Giants": [[30, 14, 13], [30, 30, 16], [27, 30, 16]], "Painted World of Ariamis,The Sunless City": [[5, 14, 16], [5, 21, 16], [27, 21, 16]], "Executioner Chariot,Tomb of Giants,The Sunless City": [[30, 10, 16], [10, 14, 13]], "Iron Keep,Executioner Chariot,The Sunless City": [[3, 10, 16]], "The Sunless City": [[27, 14, 16]], "Executioner Chariot,The Sunless City,Darkroot": [[10, 14, 17], [10, 8, 16]], "Tomb of Giants,Explorers,The Sunless City": [[26, 14, 13], [26, 30, 16]], "Iron Keep,Tomb of Giants,The Sunless City": [[3, 14, 13], [3, 30, 16]], "The Sunless City,Explorers": [[26, 14, 16]], "Tomb of Giants,Painted World of Ariamis,The Sunless City": [[27, 21, 13], [30, 14, 20]], "Iron Keep,Painted World of Ariamis,The Sunless City": [[3, 21, 16], [3, 9, 16]]}, "original": [22, 24, 17]}